<?xml version="1.0" encoding="utf-8" ?>
<Environment>
    <ServiceConnectionInfo>
        <CertificateFileName>aduxptest.pfx</CertificateFileName>
        <!-- is overriden by environment variable named "ServiceUrl" -->
        <Url>https://service.activedirectory.windowsazure.com:444</Url>
        <CertificatePassword>p@ssword1</CertificatePassword>
        <RestReceiveTimeout>180</RestReceiveTimeout>
        <RestSendTimeout>180</RestSendTimeout>
        <RestOpenTimeout>180</RestOpenTimeout>
        <RestCloseTimeout>180</RestCloseTimeout>
        <ODataTimeout>180</ODataTimeout>
        <StsConfiguration>
          <StsTokenEndpoint>https://login.windows.net/{0}/oauth2/token</StsTokenEndpoint>
          <ClientId>73299c18-d596-42d1-a718-0dc9833ecc70</ClientId>
          <Resource>0000000c-0000-0000-c000-000000000000</Resource>
          <LiveIdAudience>urn:federation:MicrosoftOnline</LiveIdAudience>
          <LiveIdEndpoint>https://login.live.com</LiveIdEndpoint>
        </StsConfiguration>
    </ServiceConnectionInfo>
    <BoxEmailUser>boxemuser@live.com</BoxEmailUser>
    <UserNamePrefix>test_aad_</UserNamePrefix>
    <WebRoleUrl>https://account.activedirectory.windowsazure.com</WebRoleUrl>
    <OrganizationNamePrefix>test_test_aad_</OrganizationNamePrefix>
    <LiveIdTestPuidPrefix>AAA</LiveIdTestPuidPrefix>
    <OrgIdTestPuidPrefix>BBB</OrgIdTestPuidPrefix>
    <RetryWaitTimeInMilliseconds>500</RetryWaitTimeInMilliseconds>
    <NumberOfRetries>40</NumberOfRetries>
    <Tenants>
        <TenantInfo>
            <Users>
                <TestUser>
                    <Kind>LiveId</Kind>
                    <ScenarioType>TenantLimitReached</ScenarioType>
                    <Puid>AAA37FFF8FC81000</Puid>
                    <ConsumerPuid>AAA37FFF8FC81000</ConsumerPuid>
                    <UserPrincipalName>TenantLimitReached@live.com</UserPrincipalName>
                </TestUser>
                <TestUser>
                    <Kind>LiveId</Kind>
                    <UserRole>User</UserRole>
                    <Puid>AAA37CCC8FC81000</Puid>
                    <ConsumerPuid>AAA37CCC8FC81000</ConsumerPuid>
                    <UserPrincipalName>user@live-int.com</UserPrincipalName>
                </TestUser>
                <TestUser>
                    <Kind>LiveId</Kind>
                    <!-- puid 00034001B42D71D6 -->
                    <UserPrincipalName>aduxptest_liveid@live.com</UserPrincipalName>
                    <Password>Password!1</Password>
                    <TenantIdentifier>5e74ff28-75c4-43fe-b97b-5434ad8908b7</TenantIdentifier>
                    <UseTokenAuth>true</UseTokenAuth>
                </TestUser>
                <TestUser>
                    <Kind>OrgId</Kind>
                    <Puid>1003BFFD8761CB75</Puid>
                    <ConsumerPuid></ConsumerPuid>
                    <UserPrincipalName>admin@aduxpTestProd.onmicrosoft.com</UserPrincipalName>
                    <Password>Password!1</Password>
                    <TenantId>e9904af4-05ca-4608-81d0-929aea7afe46</TenantId>
                    <TenantIdentifier>aduxpTestProd.onmicrosoft.com</TenantIdentifier>
                    <UseTokenAuth>true</UseTokenAuth>
                </TestUser>
                <TestUser>
                  <Kind>OrgId</Kind>
                  <!-- puid 10037FFE8953BB4B -->
                  <ScenarioType>RmsSubscribed</ScenarioType>
                  <TenantIdentifier>RMSADUXPTest.onmicrosoft.com</TenantIdentifier>
                  <UserPrincipalName>admin@RMSADUXPTest.onmicrosoft.com</UserPrincipalName>
                  <Password>Pa$$w0rd</Password>
                  <UseTokenAuth>true</UseTokenAuth>
                </TestUser>
                <TestUser>
                    <Kind>OrgId</Kind>
                    <ScenarioType>SubscriptionAndLicense</ScenarioType>
                    <TenantIdentifier>aduxpLicenseTest.onmicrosoft.com</TenantIdentifier>
                    <!-- Puid 10033FFF8907680C -->
                    <UserPrincipalName>admin@aduxpLicenseTest.onmicrosoft.com</UserPrincipalName>
                    <Password>P0rsche911</Password>
                    <UseTokenAuth>true</UseTokenAuth>
                </TestUser>
                <TestUser>
                    <Kind>OrgId</Kind>
                    <ScenarioType>TenantWithCommerceBackedPaidSubscription</ScenarioType>
                    <TenantIdentifier>TestAADpProd.onmicrosoft.com</TenantIdentifier>
                    <!-- PUID 10033FFF89DB97B5 -->
                    <UserPrincipalName>jamesw@TestAADpProd.onmicrosoft.com</UserPrincipalName>
                    <Password>P0rsche911</Password>
                    <UseTokenAuth>true</UseTokenAuth>
                </TestUser>
                <TestUser>
                    <Kind>LiveId</Kind>
                    <ScenarioType>TenantWithMoreThanOneUser</ScenarioType>
                    <TenantIdentifier>0f1c212d-d153-419f-91a8-36a6637c2571</TenantIdentifier>
                    <UserPrincipalName>aduxpLiveIdGuest@outlook.com</UserPrincipalName>
                    <!--<ConsumerPuid>00037FFECA37C48C</ConsumerPuid>-->
                    <Password>P0rsche911</Password>
                    <UseTokenAuth>true</UseTokenAuth>
                </TestUser>
                <TestUser>
                    <Kind>OrgId</Kind>
                    <ScenarioType>TenantWithNgvlServicePrincipal</ScenarioType>
                    <TenantIdentifier>aadtestngvlsp.onmicrosoft.com</TenantIdentifier>
                    <!--Puid 10030000891A49E6 -->
                    <UserPrincipalName>admin@aadtestngvlsp.onmicrosoft.com</UserPrincipalName>
                    <Password>P0rsche911</Password>
                    <UseTokenAuth>true</UseTokenAuth>
                </TestUser>
                <TestUser>
                    <Kind>OrgId</Kind>
                    <ScenarioType>TenantWithNgvlServicePrincipal</ScenarioType>
                    <UserRole>User</UserRole>
                    <TenantIdentifier>aadtestngvlsp.onmicrosoft.com</TenantIdentifier>
                    <!--Puid 10037FFE89269727 -->
                    <UserPrincipalName>iw@aadtestngvlsp.onmicrosoft.com</UserPrincipalName>
                    <Password>P0rsche911</Password>
                    <UseTokenAuth>true</UseTokenAuth>
                </TestUser>
                <!--<TestUser>
                  <Kind>OrgId</Kind>
                  <ScenarioType>SsgmUser</ScenarioType>
                  <TenantIdentifier>aduxpLicenseTest.onmicrosoft.com</TenantIdentifier>
                  <UserPrincipalName>SSGMUser@aduxpLicenseTest.onmicrosoft.com</UserPrincipalName>
                  <Password>P0rsche911</Password>
                  <UseTokenAuth>true</UseTokenAuth>
                </TestUser>
                <TestUser>
                  <Kind>OrgId</Kind>
                  <ScenarioType>SsgmAdmin</ScenarioType>
                  <TenantIdentifier>aduxpLicenseTest.onmicrosoft.com</TenantIdentifier>
                  <UserPrincipalName>SsgmAdmin@aduxpLicenseTest.onmicrosoft.com</UserPrincipalName>
                  <Password>P0rsche911</Password>
                  <UseTokenAuth>true</UseTokenAuth>
                </TestUser>-->

              	<TestUser>
                  <Kind>OrgId</Kind>
                  <ScenarioType>SsgmUser</ScenarioType>
                  <TenantIdentifier>panda125.onmicrosoft.com</TenantIdentifier>
                  <UserPrincipalName>ssgmUser@panda125.onmicrosoft.com</UserPrincipalName>
                  <Password>Pa$$w0rd</Password>
                  <UseTokenAuth>true</UseTokenAuth>
                </TestUser>
                <TestUser>
                  <Kind>OrgId</Kind>
                  <ScenarioType>SsgmAdmin</ScenarioType>
                  <TenantIdentifier>panda125.onmicrosoft.com</TenantIdentifier>
                  <UserPrincipalName>alex@panda125.onmicrosoft.com</UserPrincipalName>
                  <Password>Pa$$w0rd</Password>
                  <UseTokenAuth>true</UseTokenAuth>
                </TestUser>
            </Users>
        </TenantInfo>
    </Tenants>
</Environment>